{
	"info": {
		"_postman_id": "a931448b-e85d-4f11-92b1-5e5d3ebbf211",
		"name": "MIS Enterprise CRM Platform",
		"description": "API endpoints for the 4 modules: Sales, User Management, Feedback, and Complain Management.",
		"schema": "https://schema.getpostman.com/json/collection/v2.1.0/collection.json"
	},
	"item": [
		{
			"name": "Sales Module (Port 8080)",
			"item": [
				{
					"name": "Login",
					"request": {
						"method": "POST",
						"header": [
							{
								"key": "Content-Type",
								"value": "application/json"
							}
						],
						"body": {
							"mode": "raw",
							"raw": "{\n    \"username\": \"admin\",\n    \"password\": \"admin123\"\n}"
						},
						"url": {
							"raw": "http://localhost:8080/api/v1/auth/login",
							"protocol": "http",
							"host": [
								"localhost"
							],
							"port": "8080",
							"path": [
								"api",
								"v1",
								"auth",
								"login"
							]
						}
					},
					"response": []
				},
				{
					"name": "List Sales",
					"request": {
						"method": "GET",
						"header": [],
						"url": {
							"raw": "http://localhost:8080/api/v1/sales",
							"protocol": "http",
							"host": [
								"localhost"
							],
							"port": "8080",
							"path": [
								"api",
								"v1",
								"sales"
							]
						}
					},
					"response": []
				},
				{
					"name": "List Products",
					"request": {
						"method": "GET",
						"header": [],
						"url": {
							"raw": "http://localhost:8080/api/v1/products",
							"protocol": "http",
							"host": [
								"localhost"
							],
							"port": "8080",
							"path": [
								"api",
								"v1",
								"products"
							]
						}
					},
					"response": []
				}
			]
		},
		{
			"name": "User Management Module (Port 8082)",
			"item": [
				{
					"name": "Login",
					"request": {
						"method": "POST",
						"header": [
							{
								"key": "Content-Type",
								"value": "application/json"
							}
						],
						"body": {
							"mode": "raw",
							"raw": "{\n    \"username\": \"admin\",\n    \"password\": \"admin123\"\n}"
						},
						"url": {
							"raw": "http://localhost:8082/api/v1/auth/login",
							"protocol": "http",
							"host": [
								"localhost"
							],
							"port": "8082",
							"path": [
								"api",
								"v1",
								"auth",
								"login"
							]
						}
					},
					"response": []
				},
				{
					"name": "Get All Users",
					"request": {
						"method": "GET",
						"header": [],
						"url": {
							"raw": "http://localhost:8082/api/v1/users",
							"protocol": "http",
							"host": [
								"localhost"
							],
							"port": "8082",
							"path": [
								"api",
								"v1",
								"users"
							]
						}
					},
					"response": []
				}
			]
		},
		{
			"name": "Feedback Module (Port 8084)",
			"item": [
				{
					"name": "Submit Feedback",
					"request": {
						"method": "POST",
						"header": [
							{
								"key": "Content-Type",
								"value": "application/json"
							}
						],
						"body": {
							"mode": "raw",
							"raw": "{\n    \"customer_id\": \"CRM-1001\",\n    \"rating\": 5,\n    \"category\": \"Product Quality\",\n    \"comments\": \"Excellent!\"\n}"
						},
						"url": {
							"raw": "http://localhost:8084/api/feedback",
							"protocol": "http",
							"host": [
								"localhost"
							],
							"port": "8084",
							"path": [
								"api",
								"feedback"
							]
						}
					},
					"response": []
				},
				{
					"name": "Analytics Summary",
					"request": {
						"method": "GET",
						"header": [],
						"url": {
							"raw": "http://localhost:8084/api/analytics/summary",
							"protocol": "http",
							"host": [
								"localhost"
							],
							"port": "8084",
							"path": [
								"api",
								"analytics",
								"summary"
							]
						}
					},
					"response": []
				}
			]
		},
		{
			"name": "Complain Management (Port 8081)",
			"item": [
				{
					"name": "Get Complaints",
					"request": {
						"method": "GET",
						"header": [],
						"url": {
							"raw": "http://localhost:8081/api/complaints",
							"protocol": "http",
							"host": [
								"localhost"
							],
							"port": "8081",
							"path": [
								"api",
								"complaints"
							]
						}
					},
					"response": []
				},
				{
					"name": "Submit Complaint",
					"request": {
						"method": "POST",
						"header": [
							{
								"key": "Content-Type",
								"value": "application/json"
							}
						],
						"body": {
							"mode": "raw",
							"raw": "{\n    \"customer_id\": 101,\n    \"title\": \"Delayed Order\",\n    \"description\": \"My order is late!\"\n}"
						},
						"url": {
							"raw": "http://localhost:8081/api/complaints",
							"protocol": "http",
							"host": [
								"localhost"
							],
							"port": "8081",
							"path": [
								"api",
								"complaints"
							]
						}
					},
					"response": []
				}
			]
		}
	]
}
